setup.py
commandline_lib/__init__.py
commandline_lib/colorful.py
commandline_lib/exceptions.py
commandline_lib/history.py
commandline_lib/shell.py
commandline_lib/style.py
commandline_lib.egg-info/PKG-INFO
commandline_lib.egg-info/SOURCES.txt
commandline_lib.egg-info/dependency_links.txt
commandline_lib.egg-info/requires.txt
commandline_lib.egg-info/top_level.txt