Metadata-Version: 1.0
Name: commandline_lib
Version: 0.0.1
Summary: Command Line Lib
Home-page: https://www.xiezheyuan.top/commandline_lib/
Author: Xie Zheyuan
Author-email: billy03282@163.com
License: UNKNOWN
Platform: UNKNOWN
